grid/__init__.py
grid/_version.py
grid/angular.py
grid/atomgrid.py
grid/basegrid.py
grid/becke.py
grid/cubic.py
grid/hirshfeld.py
grid/molgrid.py
grid/ode.py
grid/onedgrid.py
grid/periodicgrid.py
grid/poisson.py
grid/rtransform.py
grid/utils.py
grid/data/__init__.py
grid/data/lebedev/__init__.py
grid/data/lebedev/lebedev_101_3470.npz
grid/data/lebedev/lebedev_107_3890.npz
grid/data/lebedev/lebedev_113_4334.npz
grid/data/lebedev/lebedev_119_4802.npz
grid/data/lebedev/lebedev_11_50.npz
grid/data/lebedev/lebedev_125_5294.npz
grid/data/lebedev/lebedev_131_5810.npz
grid/data/lebedev/lebedev_13_74.npz
grid/data/lebedev/lebedev_15_86.npz
grid/data/lebedev/lebedev_17_110.npz
grid/data/lebedev/lebedev_19_146.npz
grid/data/lebedev/lebedev_21_170.npz
grid/data/lebedev/lebedev_23_194.npz
grid/data/lebedev/lebedev_25_230.npz
grid/data/lebedev/lebedev_27_266.npz
grid/data/lebedev/lebedev_29_302.npz
grid/data/lebedev/lebedev_31_350.npz
grid/data/lebedev/lebedev_35_434.npz
grid/data/lebedev/lebedev_3_12.npz
grid/data/lebedev/lebedev_3_6.npz
grid/data/lebedev/lebedev_3_8.npz
grid/data/lebedev/lebedev_41_590.npz
grid/data/lebedev/lebedev_47_770.npz
grid/data/lebedev/lebedev_53_974.npz
grid/data/lebedev/lebedev_59_1202.npz
grid/data/lebedev/lebedev_5_14.npz
grid/data/lebedev/lebedev_5_18.npz
grid/data/lebedev/lebedev_65_1454.npz
grid/data/lebedev/lebedev_71_1730.npz
grid/data/lebedev/lebedev_77_2030.npz
grid/data/lebedev/lebedev_7_26.npz
grid/data/lebedev/lebedev_83_2354.npz
grid/data/lebedev/lebedev_89_2702.npz
grid/data/lebedev/lebedev_95_3074.npz
grid/data/lebedev/lebedev_9_38.npz
grid/data/proatoms/__init__.py
grid/data/proatoms/a001.npz
grid/data/proatoms/a006.npz
grid/data/proatoms/a007.npz
grid/data/proatoms/a008.npz
grid/data/prune_grid/__init__.py
grid/data/prune_grid/prune_grid_coarse.npz
grid/data/prune_grid/prune_grid_fine.npz
grid/data/prune_grid/prune_grid_g1.npz
grid/data/prune_grid/prune_grid_g2.npz
grid/data/prune_grid/prune_grid_g3.npz
qcgrid-0.0.8.post2.dist-info/LICENSE
qcgrid-0.0.8.post2.dist-info/METADATA
qcgrid-0.0.8.post2.dist-info/WHEEL
qcgrid-0.0.8.post2.dist-info/top_level.txt
qcgrid-0.0.8.post2.dist-info/RECORD
