Metadata-Version: 2.1
Name: qcgrid
Version: 0.0.8.post2
Summary: Grid performs numerical integration, interpolation and differentiation.
Author-email: QC-Devs Community <qcdevs@gmail.com>
License: GPL-3.0-or-later
Project-URL: Documentation, https://grid.qcdevs.org
Project-URL: Issues, https://github.com/theochem/grid/issues
Project-URL: Source, https://github.com/theochem/grid/
Project-URL: Changelog, https://github.com/theochem/grid/blob/main/CHANGELOG.md
Classifier: Development Status :: 5 - Production/Stable
Classifier: Environment :: Console
Classifier: License :: OSI Approved :: GNU General Public License v3 or later (GPLv3+)
Classifier: Operating System :: POSIX :: Linux
Classifier: Topic :: Scientific/Engineering :: Physics
Classifier: Topic :: Scientific/Engineering :: Chemistry
Classifier: Intended Audience :: Science/Research
Classifier: Intended Audience :: Education
Classifier: Natural Language :: English
Classifier: Programming Language :: Python :: 3.9
Classifier: Programming Language :: Python :: 3.10
Classifier: Programming Language :: Python :: 3.11
Classifier: Programming Language :: Python :: 3.12
Classifier: Programming Language :: Python :: 3.13
Requires-Python: >=3.9
License-File: LICENSE
Requires-Dist: numpy >=1.16
Requires-Dist: pytest >=8.0.0
Requires-Dist: scipy >=1.4
Requires-Dist: importlib-resources
Requires-Dist: sympy
Provides-Extra: doc
Requires-Dist: ipython ; extra == 'doc'
Requires-Dist: numpydoc ; extra == 'doc'
Requires-Dist: sphinx-copybutton ; extra == 'doc'
Requires-Dist: sphinx-autoapi ; extra == 'doc'
Requires-Dist: nbsphinx ; extra == 'doc'
Requires-Dist: nbconvert ; extra == 'doc'
Requires-Dist: sphinx-rtd-theme ; extra == 'doc'
Requires-Dist: sphinx-autodoc-typehints ; extra == 'doc'
Requires-Dist: docutils ==0.16 ; extra == 'doc'
Requires-Dist: nbsphinx-link ; extra == 'doc'
